<mockup version="5.1" minAllowVersion="5.1" ID="36A3360F-7A62-4405-8F38-C9C61FDC0941" platform="MtMobile" defaultW="375" defaultH="667" measureW="375" measureH="667" screenOrientation="MoPortrait" mobileScreenScale="1.77777779102325" clipArea="(0,0,0,0)">
  <controls controlCount="14">
    <control controlID="9C1C6769-E645-4CED-82FA-C7ACF753F63F" controlTypeID="Label" x="29" y="77" w="189" h="43" zOrder="0">
      <font family="Bodoni+MT+Poster+Compressed" displayName="Bodoni+MT+Poster+Compressed_%26_Bold" postScript="" weightStyle="Bold" weight="700" isBold="True" isItalic="False" useDefaultFontFamily="False"/>
      <text>Forgot+your+</text>
      <textColor>4292381191</textColor>
      <textSize>32</textSize>
      <lineSpacing>0</lineSpacing>
      <textStyles>[fsBold]</textStyles>
      <useDefaultTextSize>False</useDefaultTextSize>
      <selectedIndex>-1</selectedIndex>
    </control>
    <control controlID="60A5D0E9-B0CA-47E1-8799-1511C6B0CE84" controlTypeID="Icon" x="10" y="30" w="20" h="20" zOrder="1">
      <color>4292380672</color>
      <links eventType="AtClick" animate="AmSlideRight" animateAutoDelay="0" animateDuration="500">
        <link targetPageID="258889CA-8004-4D2A-ACBF-ABD70CA73D3D" linkType="ltPageLink" isApplyIncludePage="False" title="Log+in">
          <area shape="0" alt="" ID="{4B8AA623-E815-4B7E-AD05-6EAAB7CFB5F4}" coords="(0,0,20,20)"/>
        </link>
      </links>
      <icon>
        <ID/>
        <iconFontName>jdIonicons</iconFontName>
        <iconCode>62154</iconCode>
      </icon>
      <URL>D95E480717200F895E41DB6E5B869596.svg</URL>
    </control>
    <control controlID="4BB93D8B-34B9-4A74-A943-A9A8F867BE30" controlTypeID="Label" x="29" y="173" w="327" h="24" zOrder="2">
      <font family="Bodoni+MT+Poster+Compressed" displayName="Bodoni+MT+Poster+Compressed_%26_Bold" postScript="" weightStyle="Bold" weight="700" isBold="True" isItalic="False" useDefaultFontFamily="False"/>
      <text>Enter+your+email+to+find+your+account.</text>
      <textColor>4292381191</textColor>
      <textSize>18</textSize>
      <lineSpacing>0</lineSpacing>
      <textStyles>[fsBold]</textStyles>
      <useDefaultTextSize>False</useDefaultTextSize>
      <selectedIndex>-1</selectedIndex>
    </control>
    <control controlID="3481EBAC-AF58-48E6-8A75-FD6CDE9AADB6" controlTypeID="Label" x="29" y="120" w="167" h="43" zOrder="3">
      <font family="Bodoni+MT+Poster+Compressed" displayName="Bodoni+MT+Poster+Compressed_%26_Bold" postScript="" weightStyle="Bold" weight="700" isBold="True" isItalic="False" useDefaultFontFamily="False"/>
      <text>password%3F</text>
      <textColor>4292381191</textColor>
      <textSize>32</textSize>
      <lineSpacing>0</lineSpacing>
      <textStyles>[fsBold]</textStyles>
      <useDefaultTextSize>False</useDefaultTextSize>
      <selectedIndex>-1</selectedIndex>
    </control>
    <control controlID="D6BB9196-574F-4F5F-A1FF-95AD1E2492FD" controlTypeID="Label" x="29" y="244" w="146" h="24" zOrder="4">
      <font family="Bodoni+MT+Poster+Compressed" displayName="Bodoni+MT+Poster+Compressed_%26_Bold" postScript="" weightStyle="Bold" weight="700" isBold="True" isItalic="False" useDefaultFontFamily="False"/>
      <text>EMAIL+ADDRESS</text>
      <textColor>4292381191</textColor>
      <textSize>18</textSize>
      <lineSpacing>0</lineSpacing>
      <textStyles>[fsBold]</textStyles>
      <useDefaultTextSize>False</useDefaultTextSize>
      <selectedIndex>-1</selectedIndex>
    </control>
    <control controlID="BE03BE2C-86BC-4FA7-9F3F-60A849714A21" controlTypeID="Line" x="29" y="307" w="317" h="2" zOrder="5">
      <color>4292381191</color>
      <font family="Segoe+UI" displayName="Segoe+UI" postScript="" weightStyle="Regular" weight="400" isBold="False" isItalic="False"/>
      <textSize>14</textSize>
      <lineSpacing>0</lineSpacing>
      <selectedIndex>-1</selectedIndex>
      <controlPoint>(159,1)</controlPoint>
      <startPoint>(1,1)</startPoint>
      <endPoint>(317,1)</endPoint>
    </control>
    <control controlID="A4F9AC0C-D330-4043-B99E-7569783459CD" controlTypeID="TextInput" x="32" y="268" w="313" h="39" zOrder="6">
      <borderColor>4294967295</borderColor>
      <interactiveData>
        <entry title="">
          <area shape="0" alt="" ID="{7E11ADB7-BCE1-43BE-B1E8-6F3CF523DF86}" coords="(0,0,313,39)"/>
          <events title="">
            <event eventType="atClick" isChecked="True">
              <behaviour title="" isChecked="True" isWait="False" isLoop="False" execMode="emParallel">
                <target targetID="02109405-2C65-4E4E-968D-C093973D8390" isChecked="True" isAutoRecovery="False" isLoop="False" execMode="emSequence">
                  <command name="Popup State Change" isChecked="True" descrition="">
                    <param name="AniInterpolation" value="0" varType="3" description=""/>
                    <param name="AniDuration" value="200" varType="3" description=""/>
                    <param name="AniAutoReverse" value="False" varType="11" description=""/>
                    <param name="AniLoop" value="False" varType="11" description=""/>
                    <param name="AniInterpolationTypeOut" value="False" varType="11" description=""/>
                    <param name="Delay" value="0" varType="3" description=""/>
                    <param name="Value" value="2" varType="3" description=""/>
                    <param name="AniType" value="0" varType="3" description=""/>
                  </command>
                </target>
              </behaviour>
            </event>
          </events>
        </entry>
      </interactiveData>
      <font family="Bodoni+MT+Poster+Compressed" displayName="Bodoni+MT+Poster+Compressed" postScript="" weightStyle="Regular" weight="300" isBold="False" isItalic="False" useDefaultFontFamily="False"/>
      <textColor>4292381191</textColor>
      <textSize>24</textSize>
      <lineSpacing>0</lineSpacing>
      <useDefaultTextSize>False</useDefaultTextSize>
      <selectedIndex>-1</selectedIndex>
    </control>
    <control controlID="E276AF13-662B-43C9-8452-C40EC3E80AD7" controlTypeID="Icon" x="304" y="556" w="51" h="51" zOrder="7">
      <color>4292381191</color>
      <links eventType="AtClick" animate="AmSlideRight" animateAutoDelay="0" animateDuration="500">
        <link targetPageID="258889CA-8004-4D2A-ACBF-ABD70CA73D3D" linkType="ltPageLink" isApplyIncludePage="False" title="Log+in">
          <area shape="0" alt="" ID="{3F2B4562-034E-4A20-81F4-D18BCB912C43}" coords="(0,0,51,51)"/>
        </link>
      </links>
      <icon>
        <ID/>
        <iconFontName>jdIonicons</iconFontName>
        <iconCode>61733</iconCode>
      </icon>
      <URL>2D780716D3D89B2EFB0155599BA0A89F.svg</URL>
    </control>
    <control controlID="7A80B90C-3184-4D24-9602-24E33A23E83F" controlTypeID="StatusBar(IOS)" x="0" y="0" w="375" h="20" zOrder="8">
      <color>4292380672</color>
      <IsAutoTextColor>False</IsAutoTextColor>
    </control>
    <control controlID="02109405-2C65-4E4E-968D-C093973D8390" controlTypeID="PopupPanel" x="-159" y="307" w="46" h="46" zOrder="9">
      <caption>Keyboard</caption>
      <color>4288256409</color>
      <groupChildrenDescriptors>
        <control controlID="6EA2C105-08A7-4146-9E0E-DBABDE77EF46" controlTypeID="Panel" x="0" y="0" w="375" h="667" zOrder="0">
          <locked>True</locked>
          <color>4288256409</color>
          <borderVisible>False</borderVisible>
          <canMove>False</canMove>
          <alias>background</alias>
          <groupChildrenDescriptors>
            <control controlID="4EC124C2-6A35-440E-9676-CB9205928525" controlTypeID="Border" x="0" y="0" w="375" h="667" zOrder="0">
              <borderVisible>False</borderVisible>
              <alias>borderLayer</alias>
            </control>
          </groupChildrenDescriptors>
          <thinkness>1</thinkness>
        </control>
        <control controlID="50B4FB64-20AC-4DFA-B889-CF352B289DF2" controlTypeID="PopupPanelContent" x="0" y="427" w="375" h="240" zOrder="1">
          <color>16777215</color>
          <alias>content</alias>
          <groupChildrenDescriptors>
            <control controlID="57ED005D-B942-4533-94FA-B5E7F1609ED4" controlTypeID="Keyboard" x="0" y="0" w="375" h="240" zOrder="0"/>
          </groupChildrenDescriptors>
        </control>
      </groupChildrenDescriptors>
      <isBackgroundFade>True</isBackgroundFade>
      <aniType_Mobile>aniMoveUp</aniType_Mobile>
    </control>
  </controls>
  <param>
    <backgroundColor>4294967295</backgroundColor>
    <fontSize>0</fontSize>
    <fontFamily/>
    <guideLines/>
  </param>
</mockup>